{
  "meta": {
    "page": {
      "currentPage": 157,
      "from": 1561,
      "lastPage": 944,
      "perPage": 10,
      "to": 1570,
      "total": 9434
    }
  },
  "data": [
    {
      "type": "tdpseTerbit",
      "id": 7960,
      "attributes": {
        "nomor_pb_umku": "912020447065100230007",
        "nama": "ACAINTR.COM",
        "website": "-",
        "sektor": "Sektor Keuangan",
        "nama_perusahaan": "ASURANSI CENTRAL ASIA",
        "tanggal_daftar": "2022-07-20",
        "nomor_tanda_daftar": "005454.08/DJAI.PSE/07/2022",
        "qr_code": "https://pse.kominfo.go.id/storage/images/qr_code/3f1473b0d786da41ebcf93f9dee67b96.png",
        "status_id": "TERDAFTAR",
        "sistem_elektronik_id": 7875
      }
    },
    {
      "type": "tdpseTerbit",
      "id": 7900,
      "attributes": {
        "nomor_pb_umku": "912020447065100230006",
        "nama": "ACA-POCKET.COM",
        "website": "aca-pocket.com",
        "sektor": "Sektor Keuangan",
        "nama_perusahaan": "ASURANSI CENTRAL ASIA",
        "tanggal_daftar": "2022-07-20",
        "nomor_tanda_daftar": "005454.07/DJAI.PSE/07/2022",
        "qr_code": "https://pse.kominfo.go.id/storage/images/qr_code/d9bbc464eb6ff9302a6e87195f97716a.png",
        "status_id": "TERDAFTAR",
        "sistem_elektronik_id": 7818
      }
    },
    {
      "type": "tdpseTerbit",
      "id": 7899,
      "attributes": {
        "nomor_pb_umku": "912020447065100230006",
        "nama": "ACA-EPOLIS.COM",
        "website": "aca-epolis.com",
        "sektor": "Sektor Keuangan",
        "nama_perusahaan": "ASURANSI CENTRAL ASIA",
        "tanggal_daftar": "2022-07-20",
        "nomor_tanda_daftar": "005454.06/DJAI.PSE/07/2022",
        "qr_code": "https://pse.kominfo.go.id/storage/images/qr_code/4dad3cc6ff0dbf402e9778aa5b7d9de4.png",
        "status_id": "TERDAFTAR",
        "sistem_elektronik_id": 7811
      }
    },
    {
      "type": "tdpseTerbit",
      "id": 7794,
      "attributes": {
        "nomor_pb_umku": "912020447065100230005",
        "nama": "MITRACA.CO.ID",
        "website": "mitraca.co.id",
        "sektor": "Sektor Keuangan",
        "nama_perusahaan": "ASURANSI CENTRAL ASIA",
        "tanggal_daftar": "2022-07-20",
        "nomor_tanda_daftar": "005454.05/DJAI.PSE/07/2022",
        "qr_code": "https://pse.kominfo.go.id/storage/images/qr_code/07f86e22d6f7bf72cbc733e85a5ad9af.png",
        "status_id": "TERDAFTAR",
        "sistem_elektronik_id": 7701
      }
    },
    {
      "type": "tdpseTerbit",
      "id": 7754,
      "attributes": {
        "nomor_pb_umku": "912020447065100230004",
        "nama": "ACA.CO.ID",
        "website": "aca.co.id",
        "sektor": "Sektor Keuangan",
        "nama_perusahaan": "ASURANSI CENTRAL ASIA",
        "tanggal_daftar": "2022-07-20",
        "nomor_tanda_daftar": "005454.04/DJAI.PSE/07/2022",
        "qr_code": "https://pse.kominfo.go.id/storage/images/qr_code/69c5be1405808fa73cb70b82dc1444b6.png",
        "status_id": "TERDAFTAR",
        "sistem_elektronik_id": 7666
      }
    },
    {
      "type": "tdpseTerbit",
      "id": 7701,
      "attributes": {
        "nomor_pb_umku": "912020447065100230003",
        "nama": "B2BACA.COM",
        "website": "b2baca.com",
        "sektor": "Sektor Keuangan",
        "nama_perusahaan": "ASURANSI CENTRAL ASIA",
        "tanggal_daftar": "2022-07-20",
        "nomor_tanda_daftar": "005454.03/DJAI.PSE/07/2022",
        "qr_code": "https://pse.kominfo.go.id/storage/images/qr_code/8cc6a9692ed66c242e22c1b1b02368b7.png",
        "status_id": "TERDAFTAR",
        "sistem_elektronik_id": 7612
      }
    },
    {
      "type": "tdpseTerbit",
      "id": 7647,
      "attributes": {
        "nomor_pb_umku": "912020447065100230002",
        "nama": "KLIKACA.COM",
        "website": "klikaca.com",
        "sektor": "Sektor Keuangan",
        "nama_perusahaan": "ASURANSI CENTRAL ASIA",
        "tanggal_daftar": "2022-07-20",
        "nomor_tanda_daftar": "005454.02/DJAI.PSE/07/2022",
        "qr_code": "https://pse.kominfo.go.id/storage/images/qr_code/9c8b862a140edc2777034ab371c4d1ba.png",
        "status_id": "TERDAFTAR",
        "sistem_elektronik_id": 7546
      }
    },
    {
      "type": "tdpseTerbit",
      "id": 7545,
      "attributes": {
        "nomor_pb_umku": "912020447065100230001",
        "nama": "ACA-MOBILE.COM",
        "website": "aca-mobile.com",
        "sektor": "Sektor Keuangan",
        "nama_perusahaan": "ASURANSI CENTRAL ASIA",
        "tanggal_daftar": "2022-07-20",
        "nomor_tanda_daftar": "005454.01/DJAI.PSE/07/2022",
        "qr_code": "https://pse.kominfo.go.id/storage/images/qr_code/0c9f1e258786829774b8216a8739ca4d.png",
        "status_id": "TERDAFTAR",
        "sistem_elektronik_id": 7369
      }
    },
    {
      "type": "tdpseTerbit",
      "id": 7364,
      "attributes": {
        "nomor_pb_umku": "812000388033400040002",
        "nama": "MYSPIL",
        "website": "myspil.com",
        "sektor": "Sektor Transportasi",
        "nama_perusahaan": "SALAM PACIFIC INDONESIA LINES",
        "tanggal_daftar": "2022-07-20",
        "nomor_tanda_daftar": "005453.01/DJAI.PSE/07/2022",
        "qr_code": "https://pse.kominfo.go.id/storage/images/qr_code/d7dce27e0bbe59a60b854b67c1fce7d9.png",
        "status_id": "TERDAFTAR",
        "sistem_elektronik_id": 7261
      }
    },
    {
      "type": "tdpseTerbit",
      "id": 7673,
      "attributes": {
        "nomor_pb_umku": "912050778158700010001",
        "nama": "PT. BPR SWADHANAMAS PAKTO",
        "website": "bprswadhanamaspakto.co.id",
        "sektor": "Sektor Keuangan",
        "nama_perusahaan": "BANK PERKREDITAN RAKYAT SWADHANAMAS PAKTO",
        "tanggal_daftar": "2022-07-20",
        "nomor_tanda_daftar": "005452.01/DJAI.PSE/07/2022",
        "qr_code": "https://pse.kominfo.go.id/storage/images/qr_code/700044261a47debf911191daf7d8071c.png",
        "status_id": "TERDAFTAR",
        "sistem_elektronik_id": 7579
      }
    }
  ]
}