{
  "meta": {
    "page": {
      "currentPage": 186,
      "from": 1851,
      "lastPage": 1005,
      "perPage": 10,
      "to": 1860,
      "total": 10048
    }
  },
  "data": [
    {
      "type": "tdpseTerbit",
      "id": 7918,
      "attributes": {
        "nomor_pb_umku": "126900068197100090001",
        "nama": "OCJEK",
        "website": "-",
        "sektor": "Sektor Transportasi, Sektor Teknologi Informasi dan Komunikasi",
        "nama_perusahaan": "CAHAYA LAMANDAU",
        "tanggal_daftar": "2022-07-20",
        "nomor_tanda_daftar": "005633.01/DJAI.PSE/07/2022",
        "qr_code": "https://pse.kominfo.go.id/storage/images/qr_code/8697ad84717fbfa592bcc9d688676b01.png",
        "status_id": "TERDAFTAR",
        "sistem_elektronik_id": 7833
      }
    },
    {
      "type": "tdpseTerbit",
      "id": 7817,
      "attributes": {
        "nomor_pb_umku": "912040174219100010001",
        "nama": "ASSIST",
        "website": "-",
        "sektor": "Sektor Keuangan",
        "nama_perusahaan": "BANK PERKREDITAN RAKYAT ANUGERAHDHARMA YUWANA JEMBER",
        "tanggal_daftar": "2022-07-20",
        "nomor_tanda_daftar": "005632.01/DJAI.PSE/07/2022",
        "qr_code": "https://pse.kominfo.go.id/storage/images/qr_code/5900f8b5be51fc97a8dd77942c795742.png",
        "status_id": "TERDAFTAR",
        "sistem_elektronik_id": 7736
      }
    },
    {
      "type": "tdpseTerbit",
      "id": 7729,
      "attributes": {
        "nomor_pb_umku": "022020471114800010001",
        "nama": "BKKPURWOREJO.COM",
        "website": "bkkpurworejo.com",
        "sektor": "Sektor Keuangan",
        "nama_perusahaan": "BANK PERKREDITAN RAKYAT BADAN KREDIT KECAMATAN PURWOREJO",
        "tanggal_daftar": "2022-07-20",
        "nomor_tanda_daftar": "005631.01/DJAI.PSE/07/2022",
        "qr_code": "https://pse.kominfo.go.id/storage/images/qr_code/7fe3799e1c6b6ca8885a5df78b6414e2.png",
        "status_id": "TERDAFTAR",
        "sistem_elektronik_id": 7638
      }
    },
    {
      "type": "tdpseTerbit",
      "id": 7990,
      "attributes": {
        "nomor_pb_umku": "110522001763500000001",
        "nama": "BANK PERKREDITAN RAKYAT DANA NIAGA 1",
        "website": "bprdananiaga.co.id",
        "sektor": "Sektor Keuangan",
        "nama_perusahaan": "BANK PERKREDITAN RAKYAT DANA NIAGA",
        "tanggal_daftar": "2022-07-20",
        "nomor_tanda_daftar": "005629.02/DJAI.PSE/07/2022",
        "qr_code": "https://pse.kominfo.go.id/storage/images/qr_code/c752dd66102236875a058f5c166bb36b.png",
        "status_id": "TERDAFTAR",
        "sistem_elektronik_id": 7910
      }
    },
    {
      "type": "tdpseTerbit",
      "id": 7917,
      "attributes": {
        "nomor_pb_umku": "912011301063400010001",
        "nama": "WEBSITE COMPANY PROFELE",
        "website": "bprbkkgrogol.co.id",
        "sektor": "Sektor Teknologi Informasi dan Komunikasi",
        "nama_perusahaan": "BANK PERKREDITAN RAKYAT BADAN KREDIT KECAMATAN GROGOL PERSERODA",
        "tanggal_daftar": "2022-07-20",
        "nomor_tanda_daftar": "005628.01/DJAI.PSE/07/2022",
        "qr_code": "https://pse.kominfo.go.id/storage/images/qr_code/e252e9815c2fbcaa9056287853ad50a4.png",
        "status_id": "TERDAFTAR",
        "sistem_elektronik_id": 7824
      }
    },
    {
      "type": "tdpseTerbit",
      "id": 9126,
      "attributes": {
        "nomor_pb_umku": "022010258133400010001",
        "nama": "LOYAL.ID",
        "website": "loyal.id",
        "sektor": "Sektor Teknologi Informasi dan Komunikasi",
        "nama_perusahaan": "LOYAL MEMBER INDONESIA",
        "tanggal_daftar": "2022-07-27",
        "nomor_tanda_daftar": "005627.01/DJAI.PSE/07/2022",
        "qr_code": "https://pse.kominfo.go.id/storage/images/qr_code/c56982e1ff6a741cd92ff4992615f3f9.png",
        "status_id": "TERDAFTAR",
        "sistem_elektronik_id": 9034
      }
    },
    {
      "type": "tdpseTerbit",
      "id": 7877,
      "attributes": {
        "nomor_pb_umku": "080722003667200000001",
        "nama": "BANK ABDI",
        "website": "bankabdi.co.id",
        "sektor": "Sektor Keuangan",
        "nama_perusahaan": "BANK PERKREDITAN RAKYAT AKAR BUDAYA DANA INDONESIA",
        "tanggal_daftar": "2022-07-20",
        "nomor_tanda_daftar": "005624.01/DJAI.PSE/07/2022",
        "qr_code": "https://pse.kominfo.go.id/storage/images/qr_code/1da851d53a793e9f370808ee4fafc40f.png",
        "status_id": "TERDAFTAR",
        "sistem_elektronik_id": 7702
      }
    },
    {
      "type": "tdpseTerbit",
      "id": 7896,
      "attributes": {
        "nomor_pb_umku": "124200032054700020004",
        "nama": "AKTIVITAS TEKNOLOGI INFORMASI ONLINE",
        "website": "otr.id",
        "sektor": "Sektor Perdagangan, Sektor Teknologi Informasi dan Komunikasi",
        "nama_perusahaan": "INOVASI MERAH PUTIH",
        "tanggal_daftar": "2022-07-20",
        "nomor_tanda_daftar": "005623.04/DJAI.PSE/07/2022",
        "qr_code": "https://pse.kominfo.go.id/storage/images/qr_code/0fd940ba02ab0c9b2c33c618d68c59f4.png",
        "status_id": "TERDAFTAR",
        "sistem_elektronik_id": 7783
      }
    },
    {
      "type": "tdpseTerbit",
      "id": 7839,
      "attributes": {
        "nomor_pb_umku": "124200032054700020003",
        "nama": "SISTEM PERDAGANGAN ONLINE",
        "website": "otr.id",
        "sektor": "Sektor Perdagangan, Sektor Teknologi Informasi dan Komunikasi",
        "nama_perusahaan": "INOVASI MERAH PUTIH",
        "tanggal_daftar": "2022-07-20",
        "nomor_tanda_daftar": "005623.03/DJAI.PSE/07/2022",
        "qr_code": "https://pse.kominfo.go.id/storage/images/qr_code/10884a93d330971b1c4be932f06f7d18.png",
        "status_id": "TERDAFTAR",
        "sistem_elektronik_id": 7751
      }
    },
    {
      "type": "tdpseTerbit",
      "id": 7801,
      "attributes": {
        "nomor_pb_umku": "124200032054700020002",
        "nama": "PENJUALAN MOBIL ONLINE",
        "website": "otr.id",
        "sektor": "Sektor Perdagangan, Sektor Teknologi Informasi dan Komunikasi",
        "nama_perusahaan": "INOVASI MERAH PUTIH",
        "tanggal_daftar": "2022-07-20",
        "nomor_tanda_daftar": "005623.02/DJAI.PSE/07/2022",
        "qr_code": "https://pse.kominfo.go.id/storage/images/qr_code/707db21e91ad9dd014afd8b68adce685.png",
        "status_id": "TERDAFTAR",
        "sistem_elektronik_id": 7722
      }
    }
  ]
}