{
  "meta": {
    "page": {
      "currentPage": 697,
      "from": 6961,
      "lastPage": 1038,
      "perPage": 10,
      "to": 6970,
      "total": 10380
    }
  },
  "data": [
    {
      "type": "tdpseTerbit",
      "id": 2731,
      "attributes": {
        "nomor_pb_umku": null,
        "nama": "PENGEMBANGAN APLIKASI",
        "website": "-",
        "sektor": "Sektor Teknologi Informasi dan Komunikasi",
        "nama_perusahaan": "ADHI MULIA GROUP",
        "tanggal_daftar": "2021-12-13",
        "nomor_tanda_daftar": "001753.01/DJAI.PSE/12/2021",
        "qr_code": "https://pse.kominfo.go.id/storage/images/qr_code/461b30aad033536ea5d9255a137e6a26.png",
        "status_id": "TERDAFTAR",
        "sistem_elektronik_id": 1802
      }
    },
    {
      "type": "tdpseTerbit",
      "id": 2730,
      "attributes": {
        "nomor_pb_umku": null,
        "nama": "YUKDIGI",
        "website": "yukdigi.net",
        "sektor": "Sektor Perdagangan, Sektor Teknologi Informasi dan Komunikasi",
        "nama_perusahaan": "MUHAMMAD ARI TAUFAN",
        "tanggal_daftar": "2021-12-12",
        "nomor_tanda_daftar": "001752.01/DJAI.PSE/12/2021",
        "qr_code": "https://pse.kominfo.go.id/storage/images/qr_code/19105fec2594853a248002bd158e7ec8.png",
        "status_id": "TERDAFTAR",
        "sistem_elektronik_id": 2827
      }
    },
    {
      "type": "tdpseTerbit",
      "id": 2729,
      "attributes": {
        "nomor_pb_umku": null,
        "nama": "ksp mitra bahagia",
        "website": "-",
        "sektor": "Sektor Keuangan",
        "nama_perusahaan": "KSP MITRA BAHAGIA",
        "tanggal_daftar": "2021-12-12",
        "nomor_tanda_daftar": "001751.01/DJAI.PSE/12/2021",
        "qr_code": "https://pse.kominfo.go.id/storage/images/qr_code/402939dd7a3133afbbff61f0946d0724.png",
        "status_id": "TERDAFTAR",
        "sistem_elektronik_id": 1727
      }
    },
    {
      "type": "tdpseTerbit",
      "id": 5564,
      "attributes": {
        "nomor_pb_umku": "111221001339800010006",
        "nama": "COVIT",
        "website": "co.vit.co.id",
        "sektor": "Sektor Teknologi Informasi dan Komunikasi",
        "nama_perusahaan": "VROMEDIA INFORMATIKA TEKNOLOGI",
        "tanggal_daftar": "2022-07-14",
        "nomor_tanda_daftar": "001750.05/DJAI.PSE/07/2022",
        "qr_code": "https://pse.kominfo.go.id/storage/images/qr_code/d66b32cdea93916b5061b82e3ac7ab4c.png",
        "status_id": "TERDAFTAR",
        "sistem_elektronik_id": 5436
      }
    },
    {
      "type": "tdpseTerbit",
      "id": 5224,
      "attributes": {
        "nomor_pb_umku": "111221001339800010005",
        "nama": "ADVIT",
        "website": "-",
        "sektor": "Sektor Teknologi Informasi dan Komunikasi",
        "nama_perusahaan": "VROMEDIA INFORMATIKA TEKNOLOGI",
        "tanggal_daftar": "2022-07-08",
        "nomor_tanda_daftar": "001750.04/DJAI.PSE/07/2022",
        "qr_code": "https://pse.kominfo.go.id/storage/images/qr_code/aaec482415b9065f3189e81adf58eea7.png",
        "status_id": "TERDAFTAR",
        "sistem_elektronik_id": 5094
      }
    },
    {
      "type": "tdpseTerbit",
      "id": 2787,
      "attributes": {
        "nomor_pb_umku": null,
        "nama": "GoVIT",
        "website": "-",
        "sektor": "Sektor Teknologi Informasi dan Komunikasi",
        "nama_perusahaan": "VROMEDIA INFORMATIKA TEKNOLOGI",
        "tanggal_daftar": "2021-12-17",
        "nomor_tanda_daftar": "001750.03/DJAI.PSE/12/2021",
        "qr_code": "https://pse.kominfo.go.id/storage/images/qr_code/16255ba44e11a3b72ea60abd1df53250.png",
        "status_id": "TERDAFTAR",
        "sistem_elektronik_id": 1858
      }
    },
    {
      "type": "tdpseTerbit",
      "id": 2782,
      "attributes": {
        "nomor_pb_umku": null,
        "nama": "VRO",
        "website": "vromedia.com",
        "sektor": "Sektor Teknologi Informasi dan Komunikasi",
        "nama_perusahaan": "VROMEDIA INFORMATIKA TEKNOLOGI",
        "tanggal_daftar": "2021-12-17",
        "nomor_tanda_daftar": "001750.02/DJAI.PSE/12/2021",
        "qr_code": "https://pse.kominfo.go.id/storage/images/qr_code/fe5b298cf1305196c6daf0bc95dbae7e.png",
        "status_id": "TERDAFTAR",
        "sistem_elektronik_id": 1857
      }
    },
    {
      "type": "tdpseTerbit",
      "id": 2728,
      "attributes": {
        "nomor_pb_umku": null,
        "nama": "VIT",
        "website": "vit.co.id",
        "sektor": "Sektor Teknologi Informasi dan Komunikasi",
        "nama_perusahaan": "VROMEDIA INFORMATIKA TEKNOLOGI",
        "tanggal_daftar": "2021-12-12",
        "nomor_tanda_daftar": "001750.01/DJAI.PSE/12/2021",
        "qr_code": "https://pse.kominfo.go.id/storage/images/qr_code/45c9f2ea313f2b6bda09b940a93f5ee0.png",
        "status_id": "TERDAFTAR",
        "sistem_elektronik_id": 1856
      }
    },
    {
      "type": "tdpseTerbit",
      "id": 2727,
      "attributes": {
        "nomor_pb_umku": null,
        "nama": "Jassa Indonesia",
        "website": "jassa.co.id",
        "sektor": "Sektor Teknologi Informasi dan Komunikasi, Sektor Transportasi",
        "nama_perusahaan": "JASSA INDO NESIA",
        "tanggal_daftar": "2021-12-12",
        "nomor_tanda_daftar": "001749.01/DJAI.PSE/12/2021",
        "qr_code": "https://pse.kominfo.go.id/storage/images/qr_code/c7317a7a5d9591963b12e1f7464f63a2.png",
        "status_id": "TERDAFTAR",
        "sistem_elektronik_id": 1855
      }
    },
    {
      "type": "tdpseTerbit",
      "id": 2726,
      "attributes": {
        "nomor_pb_umku": null,
        "nama": "Xendit App",
        "website": "-",
        "sektor": "Sektor Teknologi Informasi dan Komunikasi",
        "nama_perusahaan": "NEX TEKNOLOGI DIGITAL",
        "tanggal_daftar": "2021-12-11",
        "nomor_tanda_daftar": "001748.01/DJAI.PSE/12/2021",
        "qr_code": "https://pse.kominfo.go.id/storage/images/qr_code/db43a42dd3ad1f8d479b180b691e253a.png",
        "status_id": "TERDAFTAR",
        "sistem_elektronik_id": 1854
      }
    }
  ]
}